IosPlistLib-0.0.1.dist-info/DESCRIPTION.rst
IosPlistLib-0.0.1.dist-info/METADATA
IosPlistLib-0.0.1.dist-info/RECORD
IosPlistLib-0.0.1.dist-info/WHEEL
IosPlistLib-0.0.1.dist-info/entry_points.txt
IosPlistLib-0.0.1.dist-info/metadata.json
IosPlistLib-0.0.1.dist-info/top_level.txt
iosplistlib/__init__.py
iosplistlib/iosplistlib.py
