Metadata-Version: 2.0
Name: IosPlistLib
Version: 0.0.1
Summary: Display and edit settings within an ipa Root.plist file in an iOS ipa.
Home-page: https://github.com/mkurdian/IosPlistLib
Author: Manuel Kurdian
Author-email: UNKNOWN
License: MIT
Keywords: iOS plist ipa
Platform: UNKNOWN
Classifier: Development Status :: 3 - Alpha
Classifier: Environment :: Console
Classifier: Intended Audience :: Developers
Classifier: Topic :: Utilities
Classifier: License :: OSI Approved :: MIT License
Classifier: Programming Language :: Python :: 3.6
